alkaline.py
alkaline-0.1.2.dist-info/LICENSE
alkaline-0.1.2.dist-info/METADATA
alkaline-0.1.2.dist-info/WHEEL
alkaline-0.1.2.dist-info/top_level.txt
alkaline-0.1.2.dist-info/RECORD
