Metadata-Version: 2.1
Name: alkaline
Version: 0.1.2
Summary: Alkaline is a way to render HTML pages with all the features of Python
Home-page: UNKNOWN
Author: Levorin Francesco
License: UNKNOWN
Platform: UNKNOWN
Classifier: Programming Language :: Python :: 3
Classifier: License :: OSI Approved :: MIT License
Classifier: Operating System :: OS Independent
Requires-Python: >=3.0
